CHANGELOG.md
LICENSE.txt
MANIFEST.in
README.md
setup.py
src/nr/__init__.py
src/nr.types.egg-info/PKG-INFO
src/nr.types.egg-info/SOURCES.txt
src/nr.types.egg-info/dependency_links.txt
src/nr.types.egg-info/requires.txt
src/nr.types.egg-info/top_level.txt
src/nr/types/__init__.py
src/nr/types/abc.py
src/nr/types/generic.py
src/nr/types/interface.py
src/nr/types/meta.py
src/nr/types/persist.py
src/nr/types/proxy.py
src/nr/types/singletons.py
src/nr/types/stream.py
src/nr/types/sumtype.py
src/nr/types/collections/__init__.py
src/nr/types/collections/_ordereddict.py
src/nr/types/struct/__init__.py
src/nr/types/struct/contrib/__init__.py
src/nr/types/struct/contrib/preprocessor.py
src/nr/types/struct/contrib/union.py
src/nr/types/struct/contrib/yaml.py
src/nr/types/struct/core/__init__.py
src/nr/types/struct/core/adapters.py
src/nr/types/struct/core/datatypes.py
src/nr/types/struct/core/errors.py
src/nr/types/struct/core/interfaces.py
src/nr/types/struct/core/json.py
src/nr/types/struct/core/mappers.py
src/nr/types/struct/struct/__init__.py
src/nr/types/struct/struct/fields.py
src/nr/types/struct/struct/plugins.py
src/nr/types/struct/struct/struct.py
src/nr/types/utils/__init__.py
src/nr/types/utils/classdef.py
src/nr/types/utils/funcdef.py
src/nr/types/utils/function.py
src/nr/types/utils/logging.py
src/nr/types/utils/module.py
src/nr/types/utils/typing.py
src/tests/__init__.py
src/tests/test_collections.py
src/tests/test_generic.py
src/tests/test_interface.py
src/tests/test_maps_ordereddict.py
src/tests/test_meta.py
src/tests/test_proxy.py
src/tests/test_stream.py
src/tests/test_sumtype.py
src/tests/test_utils_typing.py
src/tests/struct/__init__.py
src/tests/struct/test_struct.py
src/tests/utils/__init__.py
src/tests/utils/test_funcdef.py
src/tests/utils/test_function.py