Metadata-Version: 2.1
Name: nr.types
Version: 4.0.0
Summary: Toolbox with useful Python classes and type magic.
Home-page: https://github.com/NiklasRosenstein/python-nr.types
Author: Niklas Rosenstein
Author-email: rosensteinniklas@gmail.com
License: MIT
Platform: UNKNOWN
Provides-Extra: persist
Provides-Extra: full
Provides-Extra: test
